pexels_apis/__init__.py
pexels_apis/main.py
pexels_apis/utils.py
pexels_apis-0.0.6.dist-info/LICENCE
pexels_apis-0.0.6.dist-info/METADATA
pexels_apis-0.0.6.dist-info/WHEEL
pexels_apis-0.0.6.dist-info/top_level.txt
pexels_apis-0.0.6.dist-info/RECORD
