Metadata-Version: 2.2
Name: pexels_apis
Version: 0.0.6
Summary: The Pexels API enables programmatic access to the full Pexels content library, including photos, videos
Home-page: https://github.com/mymi14s/pexels_api
Author: Emmanuel Anthony
Author-email: mymi14s@hotmail.com
Classifier: Programming Language :: Python :: 3
Classifier: License :: OSI Approved :: MIT License
Classifier: Operating System :: OS Independent
Requires-Python: >=3.7
License-File: LICENCE
